bottle_oauthproxy/__init__.py
bottle_oauthproxy/authenticator.py
bottle_oauthproxy/client.py
bottle_oauthproxy/provider.py
bottle_oauthproxy/server.py
bottle_oauthproxy-0.1.dist-info/METADATA
bottle_oauthproxy-0.1.dist-info/WHEEL
bottle_oauthproxy-0.1.dist-info/top_level.txt
bottle_oauthproxy-0.1.dist-info/RECORD
